parasync/__init__.py
parasync/main.py
parasync-0.1.6.dist-info/METADATA
parasync-0.1.6.dist-info/WHEEL
parasync-0.1.6.dist-info/entry_points.txt
parasync-0.1.6.dist-info/licenses/LICENSE
parasync-0.1.6.dist-info/RECORD
