Metadata-Version: 2.4
Name: parasync
Version: 0.1.6
Summary: parasync is a parallelized rsync tool written in Python.
Project-URL: Homepage, https://github.com/rioriost/homebrew-parasync
Project-URL: Issues, https://github.com/rioriost/homebrew-parasync/issues
Author-email: Rio Fujita <rifujita@microsoft.com>
License: MIT License
License-File: LICENSE
Requires-Python: >=3.9
Requires-Dist: psutil>=7.2.1
